{
  "original_audio_file": "C:\\Users\\Admin\\Desktop\\dat301m\\Speech_to_text\\crawl_data\\datasets\\sachnoivietnam15\\dataset\\FFK4A6_qrlI_014.wav",
  "mel_spectrogram_file": "C:\\Users\\Admin\\Desktop\\dat301m\\Speech_to_text\\preprocessing_data\\processed_dataset\\FFK4A6_qrlI_014_mel.npy",
  "mel_shape": [
    80,
    3000
  ],
  "transcript": "nhấn mạnh thực tế số người vắng mặt chỉ là thiểu số bằng cách nêu bật số lượng những người thực sự có mặt tương tự lấy khuyên hữu ích dành cho các lãnh đạo sự nghiệp là nên Công bố số lượng phần thưởng nhân viên hay các đồng nghiệp đã áp dụng cách làm được mới hệ thống phần mềm mới hay một kế hoạch chăm sóc khách hàng mới vào thói quen hàng ngày của họ Bằng cách làm như vậy các nhà lãnh đạo có thể yên tâm rằng họ đang khai thác hiệu quả bằng chứng xã hội chứ không phải biến nó thành Vũ để chống lại mình",
  "duration": 30.0,
  "sample_rate": 16000,
  "n_mels": 80,
  "n_frames": 3000
}