{
  "original_audio_file": "C:\\Users\\Admin\\Desktop\\dat301m\\Speech_to_text\\crawl_data\\datasets\\sachnoivietnam15\\dataset\\HKmoHC7rnpg_081.wav",
  "mel_spectrogram_file": "C:\\Users\\Admin\\Desktop\\dat301m\\Speech_to_text\\preprocessing_data\\processed_dataset\\HKmoHC7rnpg_081_mel.npy",
  "mel_shape": [
    80,
    3000
  ],
  "transcript": "Ông tìm cách nói tên người đó dài ba lần và dán ghi trong trí nhớ hình dáng giữa mặt người đó để khi thấy người thì liên tưởng ngay tới tên được Nếu là một nhân vật rất quan trọng ông giết ngay tình nhân vật đó trên một miếng giấy nhỏ kỹ nó tập trung tư tưởng vào nó cho nó khắc sâu trong ốc như vậy ông trùm cả tay vẫn mất Để Nhớ khi tất cả những cái đó mất thì giờ nhưng MC nói muốn lễ phép thì phải chịu nhiều hi sinh nhỏ muốn gây thiện cảm xinh bạn để ý tới quy",
  "duration": 30.0,
  "sample_rate": 16000,
  "n_mels": 80,
  "n_frames": 3000
}