{
  "original_audio_file": "C:\\Users\\Admin\\Desktop\\dat301m\\Speech_to_text\\crawl_data\\datasets\\sachnoivietnam15\\dataset\\XfFfd5nfSuk_009.wav",
  "mel_spectrogram_file": "C:\\Users\\Admin\\Desktop\\dat301m\\Speech_to_text\\preprocessing_data\\processed_dataset\\XfFfd5nfSuk_009_mel.npy",
  "mel_shape": [
    80,
    3000
  ],
  "transcript": "được nhìn nhận như thế nào đó phải là vấn đề từ suy nghĩ của khách hàng em thứ hai trở nên khác biệt không giống với việc có một sự hiện diện khác biệt sự khác biệt tự nó phần thực nhấn mạnh rằng điều làm trong một công ty trở nên khác biệt thì cũng sẽ ngay lập tức tạo ra cạnh tranh Khách hàng cần nhắc và đánh giá cái gọi là sự khác biệt dựa trên cảm nhận của họ để trở nên khác biệt các doanh nghiệp đều phải đặt khách hàng làm trọng tâm trên mỗi phụ diện khi tìm được doanh nghiệp Thực sự khác biệt thông qua",
  "duration": 30.0,
  "sample_rate": 16000,
  "n_mels": 80,
  "n_frames": 3000
}